profile_maboss/__init__.py
profile_maboss/ext_maboss.py
profile_maboss-1.0.1.21.dist-info/LICENCE
profile_maboss-1.0.1.21.dist-info/METADATA
profile_maboss-1.0.1.21.dist-info/WHEEL
profile_maboss-1.0.1.21.dist-info/top_level.txt
profile_maboss-1.0.1.21.dist-info/RECORD
