Metadata-Version: 2.1
Name: profile-maboss
Version: 1.0.1.21
Summary: A package allowing personalisation of MaBoSS models with the PROFILE methodology defined in [paper_ref]
Home-page: UNKNOWN
Author: Rémi Trimbour
Author-email: remi.trimbour@ens.fr
License: UNKNOWN
Platform: UNKNOWN
License-File: LICENCE
Requires-Dist: maboss
